lasikservice/__init__.py
lasikservice/serialconnection.py
lasikservice/service.py
lasikservice/socketserver.py
lasikservice-0.1.4.dist-info/METADATA
lasikservice-0.1.4.dist-info/RECORD
lasikservice-0.1.4.dist-info/WHEEL
lasikservice-0.1.4.dist-info/entry_points.txt
lasikservice-0.1.4.dist-info/top_level.txt
